picklefy/__init__.py
picklefy/pickle_service.py
picklefy/pickle_files/__init__.py
picklefy-0.0.3.dist-info/LICENSE
picklefy-0.0.3.dist-info/METADATA
picklefy-0.0.3.dist-info/WHEEL
picklefy-0.0.3.dist-info/top_level.txt
picklefy-0.0.3.dist-info/RECORD
