Metadata-Version: 2.1
Name: picklefy
Version: 0.0.3
Summary: Um facilitador para trabalhar com pickle files
Home-page: UNKNOWN
Author: Henrique Spencer Albuquerque
Author-email: <henriquespencer11@gmail.com>
License: UNKNOWN
Keywords: python,pickle,serialize,deserializar,arquivos,facilitador,picklefy,picklefy
Platform: UNKNOWN
Classifier: Development Status :: 1 - Planning
Classifier: Intended Audience :: Developers
Classifier: Programming Language :: Python :: 3
Classifier: Operating System :: Unix
Classifier: Operating System :: MacOS :: MacOS X
Classifier: Operating System :: Microsoft :: Windows
Classifier: Topic :: Utilities
Requires-Python: >=3.6
License-File: LICENSE
